to_3mf/__init__.py
to_3mf/slicer_project_file_editor.py
to_3mf/stl_to_3mf.py
to_3mf/threemf_config.py
to_3mf/threemf_model.py
to_3mf/xdatatree_utils.py
to_3mf-0.1.0.dist-info/METADATA
to_3mf-0.1.0.dist-info/WHEEL
to_3mf-0.1.0.dist-info/licenses/LICENSE
to_3mf-0.1.0.dist-info/RECORD
