Metadata-Version: 2.4
Name: to_3mf
Version: 0.1.0
Summary: A set of Python tools for managing the 3mf file format. Includes an STL to 3mf file converter.
Project-URL: Homepage, https://github.com/owebeeone/to_3mf
Project-URL: Bug Tracker, https://github.com/owebeeone/to_3mf/issues
Author-email: Gianni Mariani <gianni@mariani.ws>
License-File: LICENSE
Classifier: License :: OSI Approved :: GNU Lesser General Public License v2 or later (LGPLv2+)
Classifier: Operating System :: OS Independent
Classifier: Programming Language :: Python :: 3
Requires-Python: >=3.10
Requires-Dist: anchorscad-linear
Requires-Dist: anchorscad-test-tools
Requires-Dist: anchorscad-utils
Requires-Dist: datatrees
Requires-Dist: lxml
Requires-Dist: numpy
Requires-Dist: numpy-stl
Requires-Dist: pythonopenscad
Requires-Dist: xdatatrees>=0.1.0
